lightgbm_callbacks/__init__.py
lightgbm_callbacks/_base.py
lightgbm_callbacks/_early_stopping_callback.py
lightgbm_callbacks/_tqdm_callback.py
lightgbm_callbacks/py.typed
lightgbm_callbacks/sklearn/__init__.py
lightgbm_callbacks/sklearn/_base.py
lightgbm_callbacks/sklearn/_dart_early_stopping_wrapper.py
lightgbm_callbacks/sklearn/_early_stopping.py
lightgbm_callbacks-0.1.16.dist-info/LICENSE
lightgbm_callbacks-0.1.16.dist-info/METADATA
lightgbm_callbacks-0.1.16.dist-info/WHEEL
lightgbm_callbacks-0.1.16.dist-info/RECORD
