Metadata-Version: 2.1
Name: lightgbm-callbacks
Version: 0.1.16
Summary: A collection of LightGBM callbacks.
Home-page: https://github.com/34j/lightgbm-callbacks
License: MIT
Author: 34j
Author-email: 34j.95a2p@simplelogin.com
Requires-Python: >=3.8,<4.0
Classifier: Development Status :: 2 - Pre-Alpha
Classifier: Intended Audience :: Developers
Classifier: License :: OSI Approved :: MIT License
Classifier: Natural Language :: English
Classifier: Operating System :: OS Independent
Classifier: Programming Language :: Python :: 3
Classifier: Programming Language :: Python :: 3.8
Classifier: Programming Language :: Python :: 3.9
Classifier: Programming Language :: Python :: 3.10
Classifier: Programming Language :: Python :: 3.11
Classifier: Programming Language :: Python :: 3.12
Classifier: Programming Language :: Python :: 3.13
Classifier: Topic :: Software Development :: Libraries
Requires-Dist: lightgbm (>=4.0.0,<5.0.0)
Requires-Dist: scikit-learn (>=1.3.1,<2.0.0)
Requires-Dist: tqdm (>=4.65.0,<5.0.0)
Requires-Dist: typing-extensions (>=4.5.0,<5.0.0)
Project-URL: Bug Tracker, https://github.com/34j/lightgbm-callbacks/issues
Project-URL: Changelog, https://github.com/34j/lightgbm-callbacks/blob/main/CHANGELOG.md
Project-URL: Documentation, https://lightgbm-callbacks.readthedocs.io
Project-URL: Repository, https://github.com/34j/lightgbm-callbacks
